EventPython-0.0.1.data/scripts/__init__.pxd
EventPython-0.0.1.data/scripts/__init__.pyx
eventpython/__init__.py
EventPython-0.0.1.dist-info/LICENSE
EventPython-0.0.1.dist-info/METADATA
EventPython-0.0.1.dist-info/WHEEL
EventPython-0.0.1.dist-info/top_level.txt
EventPython-0.0.1.dist-info/RECORD
