Metadata-Version: 2.1
Name: EventPython
Version: 0.0.1
Summary: Event support for Python.
Home-page: UNKNOWN
Author: j_pack
Author-email: iamjojozm@icloud.com
License: UNKNOWN
Keywords: event python eventdispatcher
Platform: UNKNOWN
Classifier: License :: OSI Approved :: Python Software Foundation License
Requires-Python: >=3.6
Requires-Dist: typing (==3.7.4.3)
Requires-Dist: multiprocessing (==2.6.2.1)
